mcskinprep/__init__.py
mcskinprep/cli.py
mcskinprep/constants.py
mcskinprep/decorators.py
mcskinprep/detector.py
mcskinprep/file_processor.py
mcskinprep/skin_type.py
mcskinprep/tools.py
mcskinprep-0.3.0.dist-info/licenses/LICENSE
mcskinprep-0.3.0.dist-info/METADATA
mcskinprep-0.3.0.dist-info/WHEEL
mcskinprep-0.3.0.dist-info/entry_points.txt
mcskinprep-0.3.0.dist-info/top_level.txt
mcskinprep-0.3.0.dist-info/RECORD
