Metadata-Version: 2.4
Name: mcskinprep
Version: 0.3.0
Summary: Minecraft Skin Preprocessing Tools
Author-email: Faxuan Cai <magicianaio@gmail.com>
Project-URL: Repository, https://github.com/Layer-norm/minecraft-skin-preprocessing.git
Project-URL: Issues, https://github.com/Layer-norm/minecraft-skin-preprocessing/issues
Classifier: Development Status :: 3 - Alpha
Classifier: Programming Language :: Python :: 3 :: Only
Classifier: Programming Language :: Python :: 3.10
Classifier: Programming Language :: Python :: 3.11
Classifier: Programming Language :: Python :: 3.12
Classifier: Programming Language :: Python :: 3.13
Classifier: Programming Language :: Python :: 3.14
Requires-Python: >=3.10
License-File: LICENSE
Requires-Dist: numpy
Requires-Dist: pillow>=10.0.0
Dynamic: license-file
